ffmin/__init__.py
ffmin/foo.py
ffmin-0.0.1.dist-info/METADATA
ffmin-0.0.1.dist-info/WHEEL
ffmin-0.0.1.dist-info/licenses/LICENSE
ffmin-0.0.1.dist-info/RECORD
