Metadata-Version: 2.4
Name: ffmin
Version: 0.0.1
Summary: Optimization In Python
Project-URL: Homepage, https://blankjul.github.io/ffmin/
Project-URL: Repository, https://github.com/blankjul/ffmin
Project-URL: Documentation, https://blankjul.github.io/ffmin/
Author-email: Julian Blank <blankjul@outlook.com>
License-File: LICENSE
Keywords: python
Classifier: Intended Audience :: Developers
Classifier: Programming Language :: Python
Classifier: Programming Language :: Python :: 3
Classifier: Programming Language :: Python :: 3.9
Classifier: Programming Language :: Python :: 3.10
Classifier: Programming Language :: Python :: 3.11
Classifier: Programming Language :: Python :: 3.12
Classifier: Programming Language :: Python :: 3.13
Classifier: Topic :: Software Development :: Libraries :: Python Modules
Requires-Python: <4.0,>=3.9
